Metadata-Version: 2.1
Name: pydustry
Version: 0.1.0
Summary: A package for getting Mindustry server status and sending commands.
Home-page: https://github.com/VozdyxDev/pydustry/
Author: Vozdyx
Author-email: vozdyxdev@gmail.com
Classifier: Programming Language :: Python :: 3
Classifier: License :: OSI Approved :: MIT License
Classifier: Operating System :: OS Independent
License-File: LICENSE
